heterogeneity_index/__init__.py
heterogeneity_index/components.py
heterogeneity_index/normalization.py
heterogeneity_index/py.typed
heterogeneity_index/util.py
heterogeneity_index-0.0.2.dist-info/LICENSE
heterogeneity_index-0.0.2.dist-info/METADATA
heterogeneity_index-0.0.2.dist-info/WHEEL
heterogeneity_index-0.0.2.dist-info/top_level.txt
heterogeneity_index-0.0.2.dist-info/RECORD
