Metadata-Version: 2.1
Name: heterogeneity-index
Version: 0.0.2
Summary: A library to detect fronts using an heterogeneity index
Author-email: Clément Haëck <clement.haeck@locean.ipsl.fr>
Project-URL: Homepage, https://gitlab.in2p3.fr/biofronts/heterogeneity-index
Classifier: Programming Language :: Python :: 3
Classifier: License :: OSI Approved :: MIT License
Classifier: Operating System :: OS Independent
Classifier: Intended Audience :: Developers
Classifier: Intended Audience :: Science/Research
Classifier: Topic :: Utilities
Requires-Python: >=3.10
License-File: LICENSE
Requires-Dist: numpy >=1.24
Requires-Dist: numba >=0.57
